bleuai/__init__.py
bleuai/client.py
bleuai/exceptions.py
bleuai/types.py
bleuai-0.1.0.dist-info/licenses/LICENSE
bleuai-0.1.0.dist-info/METADATA
bleuai-0.1.0.dist-info/WHEEL
bleuai-0.1.0.dist-info/top_level.txt
bleuai-0.1.0.dist-info/RECORD
