Metadata-Version: 2.4
Name: bleuai
Version: 0.1.0
Summary: Python SDK for Bleu AI workflow execution
Home-page: https://github.com/buildbleu/bleuai-python
Author: Bleu AI
Author-email: Bleu AI <contact@buildbleu.com>
Maintainer-email: Bleu AI <contact@buildbleu.com>
License: MIT
Project-URL: Homepage, https://buildbleu.com
Project-URL: Documentation, https://docs.buildbleu.com
Project-URL: Repository, https://github.com/buildbleu/bleuai-python
Project-URL: Issues, https://github.com/buildbleu/bleuai-python/issues
Keywords: bleu,ai,workflow,automation,api,sdk
Classifier: Development Status :: 4 - Beta
Classifier: Intended Audience :: Developers
Classifier: Topic :: Software Development :: Libraries :: Python Modules
Classifier: License :: OSI Approved :: MIT License
Classifier: Programming Language :: Python :: 3
Classifier: Programming Language :: Python :: 3.7
Classifier: Programming Language :: Python :: 3.8
Classifier: Programming Language :: Python :: 3.9
Classifier: Programming Language :: Python :: 3.10
Classifier: Programming Language :: Python :: 3.11
Classifier: Operating System :: OS Independent
Requires-Python: >=3.7
License-File: LICENSE
Requires-Dist: httpx>=0.24.0
Requires-Dist: supabase>=2.0.0
Requires-Dist: realtime>=1.0.0
Provides-Extra: dev
Requires-Dist: pytest>=7.0.0; extra == "dev"
Requires-Dist: pytest-asyncio>=0.21.0; extra == "dev"
Requires-Dist: black>=23.0.0; extra == "dev"
Requires-Dist: mypy>=1.0.0; extra == "dev"
Requires-Dist: ruff>=0.1.0; extra == "dev"
Dynamic: author
Dynamic: home-page
Dynamic: license-file
Dynamic: requires-python
